cmdtree/__init__.py
cmdtree/_compat.py
cmdtree/exceptions.py
cmdtree/parser.py
cmdtree/registry.py
cmdtree/shortcuts.py
cmdtree/tree.py
cmdtree/types.py
cmdtree-0.0.5.dist-info/DESCRIPTION.rst
cmdtree-0.0.5.dist-info/METADATA
cmdtree-0.0.5.dist-info/RECORD
cmdtree-0.0.5.dist-info/WHEEL
cmdtree-0.0.5.dist-info/metadata.json
cmdtree-0.0.5.dist-info/top_level.txt
