Metadata-Version: 2.0
Name: cmdtree
Version: 0.0.5
Summary: Yet another cli tool library ,sub-command friendly, designed for cli auto-generating.
Home-page: https://github.com/winkidney/cmdtree
Author: winkidney
Author-email: winkidney@gmail.com
License: MIT
Platform: UNKNOWN
Requires-Dist: argparse
Requires-Dist: six (>=1.10.0)
